LICENSE
dj_cleavejs/__init__.py
dj_cleavejs/apps.py
dj_cleavejs/static/dj_cleave.js
dj_cleavejs/widgets.py
django_cleavejs-0.1.1.dist-info/LICENSE
django_cleavejs-0.1.1.dist-info/WHEEL
django_cleavejs-0.1.1.dist-info/METADATA
django_cleavejs-0.1.1.dist-info/RECORD
