Metadata-Version: 2.1
Name: django-cleavejs
Version: 0.1.1
Summary: Cleave.js integration for Django forms
Home-page: https://edugit.org/AlekSIS/libs/django-cleavejs
License: Apache-2.0
Keywords: django,forms,input
Author: Dominik George
Author-email: dominik.george@teckids.org
Requires-Python: >=3.7,<4.0
Classifier: Development Status :: 4 - Beta
Classifier: Environment :: Web Environment
Classifier: Framework :: Django
Classifier: Intended Audience :: Developers
Classifier: License :: OSI Approved :: Apache Software License
Classifier: Programming Language :: Python :: 3
Classifier: Programming Language :: Python :: 3.7
Classifier: Programming Language :: Python :: 3.8
Classifier: Programming Language :: Python :: 3.9
Requires-Dist: Django (>2.1,<5.0)
Project-URL: Repository, https://edugit.org/AlekSIS/libs/django-cleavejs
